MANIFEST.in
README.rst
setup.py
src/digimat/__init__.py
src/digimat.gapi.egg-info/PKG-INFO
src/digimat.gapi.egg-info/SOURCES.txt
src/digimat.gapi.egg-info/dependency_links.txt
src/digimat.gapi.egg-info/not-zip-safe
src/digimat.gapi.egg-info/requires.txt
src/digimat.gapi.egg-info/top_level.txt
src/digimat/gapi/__init__.py
src/digimat/gapi/gapi.py
src/digimat/gapi/gapicalendar.py
src/digimat/gapi/gcalscheduler.py
src/digimat/gapi/gwsheet.py